action_lipo/__init__.py
action_lipo/lipo.py
action_lipo-0.1.0.dist-info/METADATA
action_lipo-0.1.0.dist-info/WHEEL
action_lipo-0.1.0.dist-info/top_level.txt
action_lipo-0.1.0.dist-info/RECORD
