Metadata-Version: 2.4
Name: action-lipo
Version: 0.1.0
Summary: A lightweight post-optimizer for action chunks
Author-email: Suhan Park <park94@kw.ac.kr>, Dongwoo Son <ehddnths@kw.ac.kr>
Project-URL: Homepage, https://github.com/lab-dream/lipo
Requires-Dist: numpy>=1.18.0
Requires-Dist: cvxpy>=1.1.0
